Workbook
Name aporte: Simulador!$C$6
Name dividendos: Simulador!$C$15
Name dividendos_sugestao: Simulador!$D$15
Name lista_perfis: Apoio!$G$7:$G$9
Name lista_tipos: Apoio!$K$7:$K$12
Name meta_renda: Configurações!$C$9
Name patrimonio: Simulador!$C$14
Name patrimonio_meta: Simulador!$C$39
Name patrimonio_sugestao: Simulador!$D$14
Name pct_aporte: Configurações!$C$8
Name perfil: Simulador!$C$9
Name prazo_anos: Simulador!$C$7
Name salario: Configurações!$C$6
Name sugestao_aporte: Configurações!$C$10
Name tabela_evolucao: Apoio!$M$7:$Q$36
Name tabela_perfis: Apoio!$B$7:$E$24
Name taxa_mensal: Configurações!$C$7

Sheet Simulador
B1: Simulador de Renda Passiva com FIIs
B3: Quanto investir, por quanto tempo e quanto você recebe de dividendos por mês
B4: =HYPERLINK("#'Configurações'!C6","→ Configurações") -> → Configurações | C4: =HYPERLINK("#Apoio!E7","→ Apoio") -> → Apoio
B5: 1 · ENTRADAS
B6: Quanto investir por mês (R$) | C6: 1000 | D6: =sugestao_aporte -> 1800
B7: Por quantos anos | C7: 20 | D7: de 1 a 50 anos
B8: Taxa de rendimento mensal | C8: =taxa_mensal -> 0.008 | D8: altere na aba Configurações
B9: Perfil de investidor | C9: Moderado | D9: escolha na lista
B11: 2 · RESULTADO: APORTE INFORMADO × APORTE SUGERIDO
B12: Indicador | C12: Aporte informado | D12: Aporte sugerido (% do salário) | E12: Diferença
B13: Aporte mensal | C13: =aporte -> 1000 | D13: =sugestao_aporte -> 1800 | E13: =D13-C13 -> 800
B14: Patrimônio acumulado | C14: =FV(taxa_mensal,prazo_anos*12,-aporte) -> 721131.22 | D14: =FV(taxa_mensal,prazo_anos*12,-sugestao_aporte) -> 1298036.2 | E14: =D14-C14 -> 576904.98
B15: Dividendos por mês | C15: =patrimonio*taxa_mensal -> 5769.0498 | D15: =patrimonio_sugestao*taxa_mensal -> 10384.29 | E15: =D15-C15 -> 4615.2398
B16: Total investido do seu bolso | C16: =aporte*prazo_anos*12 -> 240000 | D16: =sugestao_aporte*prazo_anos*12 -> 432000 | E16: =D16-C16 -> 192000
B17: Ganho com juros compostos | C17: =patrimonio-C16 -> 481131.22 | D17: =patrimonio_sugestao-D16 -> 866036.19 | E17: =D17-C17 -> 384904.98
B19: 3 · CENÁRIOS DE 2 A 30 ANOS
B20: Prazo (anos) | C20: Patrimônio · informado | D20: Patrimônio · sugerido | E20: Dividendos/mês · informado | F20: Dividendos/mês · sugerido
B21: 2 | C21: =FV(taxa_mensal,B21*12,-aporte) -> 26343.155 | D21: =FV(taxa_mensal,B21*12,-sugestao_aporte) -> 47417.679 | E21: =C21*taxa_mensal -> 210.74524 | F21: =D21*taxa_mensal -> 379.34143
B22: 5 | C22: =FV(taxa_mensal,B22*12,-aporte) -> 76623.867 | D22: =FV(taxa_mensal,B22*12,-sugestao_aporte) -> 137922.96 | E22: =C22*taxa_mensal -> 612.99093 | F22: =D22*taxa_mensal -> 1103.3837
B23: 10 | C23: =FV(taxa_mensal,B23*12,-aporte) -> 200217.47 | D23: =FV(taxa_mensal,B23*12,-sugestao_aporte) -> 360391.44 | E23: =C23*taxa_mensal -> 1601.7398 | F23: =D23*taxa_mensal -> 2883.1316
B24: 20 | C24: =FV(taxa_mensal,B24*12,-aporte) -> 721131.22 | D24: =FV(taxa_mensal,B24*12,-sugestao_aporte) -> 1298036.2 | E24: =C24*taxa_mensal -> 5769.0498 | F24: =D24*taxa_mensal -> 10384.29
B25: 30 | C25: =FV(taxa_mensal,B25*12,-aporte) -> 2076413.2 | D25: =FV(taxa_mensal,B25*12,-sugestao_aporte) -> 3737543.8 | E25: =C25*taxa_mensal -> 16611.306 | F25: =D25*taxa_mensal -> 29900.351
B27: 4 · DIVISÃO DO APORTE POR PERFIL
B28: Tipo de fundo | C28: Percentual | D28: Aporte mensal | E28: Patrimônio projetado | F28: Dividendos por mês
B29: =Apoio!$K$7 -> Papel (CRI) | C29: =IFERROR(VLOOKUP(perfil&"|"&B29,tabela_perfis,4,FALSE()),0) -> 0.25 | D29: =aporte*C29 -> 250 | E29: =patrimonio*C29 -> 180282.8 | F29: =dividendos*C29 -> 1442.2624
B30: =Apoio!$K$8 -> Logística | C30: =IFERROR(VLOOKUP(perfil&"|"&B30,tabela_perfis,4,FALSE()),0) -> 0.2 | D30: =aporte*C30 -> 200 | E30: =patrimonio*C30 -> 144226.24 | F30: =dividendos*C30 -> 1153.81
B31: =Apoio!$K$9 -> Lajes Corporativas | C31: =IFERROR(VLOOKUP(perfil&"|"&B31,tabela_perfis,4,FALSE()),0) -> 0.15 | D31: =aporte*C31 -> 150 | E31: =patrimonio*C31 -> 108169.68 | F31: =dividendos*C31 -> 865.35746
B32: =Apoio!$K$10 -> Shoppings | C32: =IFERROR(VLOOKUP(perfil&"|"&B32,tabela_perfis,4,FALSE()),0) -> 0.15 | D32: =aporte*C32 -> 150 | E32: =patrimonio*C32 -> 108169.68 | F32: =dividendos*C32 -> 865.35746
B33: =Apoio!$K$11 -> Fundo de Fundos (FoF) | C33: =IFERROR(VLOOKUP(perfil&"|"&B33,tabela_perfis,4,FALSE()),0) -> 0.15 | D33: =aporte*C33 -> 150 | E33: =patrimonio*C33 -> 108169.68 | F33: =dividendos*C33 -> 865.35746
B34: =Apoio!$K$12 -> Híbridos | C34: =IFERROR(VLOOKUP(perfil&"|"&B34,tabela_perfis,4,FALSE()),0) -> 0.1 | D34: =aporte*C34 -> 100 | E34: =patrimonio*C34 -> 72113.122 | F34: =dividendos*C34 -> 576.90498
B35: Total | C35: =SUM(C29:C34) -> 1 | D35: =SUM(D29:D34) -> 1000 | E35: =SUM(E29:E34) -> 721131.22 | F35: =SUM(F29:F34) -> 5769.0498
B37: 5 · META DE RENDA: QUANTO TEMPO PARA CHEGAR LÁ
B38: Meta de dividendos por mês | C38: =meta_renda -> 5000
B39: Patrimônio necessário | C39: =IF(taxa_mensal>0,meta_renda/taxa_mensal,0) -> 625000
C40: Aporte informado | D40: Aporte sugerido
B41: Tempo para atingir a meta | C41: =IFERROR(NPER(taxa_mensal,-aporte,0,patrimonio_meta)/12,"—") -> 18.738719 | D41: =IFERROR(NPER(taxa_mensal,-sugestao_aporte,0,patrimonio_meta)/12,"—") -> 13.900473

Sheet Configurações
B1: Configurações
B4: =HYPERLINK("#Simulador!C6","← Voltar ao Simulador") -> ← Voltar ao Simulador
B5: SEUS DADOS
B6: Salário mensal líquido (R$) | C6: 6000 | E6: Valor de exemplo — substitua pelo seu salário.
B7: Rendimento mensal da carteira | C7: 0.008 | E7: Valor de exemplo (0,8% a.m.) — use o rendimento real da sua carteira.
B8: % do salário destinado ao aporte | C8: 0.3 | E8: Regra prática de 30% do salário; ajuste ao seu orçamento.
B9: Meta de dividendos por mês (R$) | C9: 5000 | E9: Valor de exemplo — quanto de renda mensal você quer alcançar.
B10: Sugestão de aporte mensal (R$) | C10: =salario*pct_aporte -> 1800 | E10: Calculado: salário × percentual. Alimenta a segunda simulação do Simulador.

Sheet Apoio
B1: Apoio — perfis de investidor e evolução anual
B4: =HYPERLINK("#Simulador!C6","← Voltar ao Simulador") -> ← Voltar ao Simulador
B5: TABELA PERFIL × TIPO DE FUNDO | G5: PERFIS E CONFERÊNCIA | K5: TIPOS DE FUNDO | M5: EVOLUÇÃO ANO A ANO (1 A 30 ANOS)
B6: Chave (perfil|tipo) | C6: Perfil | D6: Tipo de fundo | E6: Percentual | G6: Perfil | H6: Soma | I6: Status | K6: Tipo de fundo | M6: Ano | N6: Patrimônio · informado | O6: Patrimônio · sugerido | P6: Dividendos/mês · informado | Q6: Dividendos/mês · sugerido
B7: =C7&"|"&D7 -> Conservador|Papel (CRI) | C7: =$G$7 -> Conservador | D7: =$K$7 -> Papel (CRI) | E7: 0.35 | G7: Conservador | H7: =SUMIF($C$7:$C$24,G7,$E$7:$E$24) -> 1 | I7: =IF(ROUND(H7,4)=1,"OK","Revisar: deve somar 100%") -> OK | K7: Papel (CRI) | M7: 1 | N7: =FV(taxa_mensal,M7*12,-aporte) -> 12542.337 | O7: =FV(taxa_mensal,M7*12,-sugestao_aporte) -> 22576.206 | P7: =N7*taxa_mensal -> 100.33869 | Q7: =O7*taxa_mensal -> 180.60965
B8: =C8&"|"&D8 -> Conservador|Logística | C8: =$G$7 -> Conservador | D8: =$K$8 -> Logística | E8: 0.2 | G8: Moderado | H8: =SUMIF($C$7:$C$24,G8,$E$7:$E$24) -> 1 | I8: =IF(ROUND(H8,4)=1,"OK","Revisar: deve somar 100%") -> OK | K8: Logística | M8: =M7+1 -> 2 | N8: =FV(taxa_mensal,M8*12,-aporte) -> 26343.155 | O8: =FV(taxa_mensal,M8*12,-sugestao_aporte) -> 47417.679 | P8: =N8*taxa_mensal -> 210.74524 | Q8: =O8*taxa_mensal -> 379.34143
B9: =C9&"|"&D9 -> Conservador|Lajes Corporativas | C9: =$G$7 -> Conservador | D9: =$K$9 -> Lajes Corporativas | E9: 0.05 | G9: Arrojado | H9: =SUMIF($C$7:$C$24,G9,$E$7:$E$24) -> 1 | I9: =IF(ROUND(H9,4)=1,"OK","Revisar: deve somar 100%") -> OK | K9: Lajes Corporativas | M9: =M8+1 -> 3 | N9: =FV(taxa_mensal,M9*12,-aporte) -> 41528.73 | O9: =FV(taxa_mensal,M9*12,-sugestao_aporte) -> 74751.713 | P9: =N9*taxa_mensal -> 332.22984 | Q9: =O9*taxa_mensal -> 598.01371
B10: =C10&"|"&D10 -> Conservador|Shoppings | C10: =$G$7 -> Conservador | D10: =$K$10 -> Shoppings | E10: 0.1 | K10: Shoppings | M10: =M9+1 -> 4 | N10: =FV(taxa_mensal,M10*12,-aporte) -> 58238.005 | O10: =FV(taxa_mensal,M10*12,-sugestao_aporte) -> 104828.41 | P10: =N10*taxa_mensal -> 465.90404 | Q10: =O10*taxa_mensal -> 838.62727
B11: =C11&"|"&D11 -> Conservador|Fundo de Fundos (FoF) | C11: =$G$7 -> Conservador | D11: =$K$11 -> Fundo de Fundos (FoF) | E11: 0.25 | K11: Fundo de Fundos (FoF) | M11: =M10+1 -> 5 | N11: =FV(taxa_mensal,M11*12,-aporte) -> 76623.867 | O11: =FV(taxa_mensal,M11*12,-sugestao_aporte) -> 137922.96 | P11: =N11*taxa_mensal -> 612.99093 | Q11: =O11*taxa_mensal -> 1103.3837
B12: =C12&"|"&D12 -> Conservador|Híbridos | C12: =$G$7 -> Conservador | D12: =$K$12 -> Híbridos | E12: 0.05 | K12: Híbridos | M12: =M11+1 -> 6 | N12: =FV(taxa_mensal,M12*12,-aporte) -> 96854.542 | O12: =FV(taxa_mensal,M12*12,-sugestao_aporte) -> 174338.18 | P12: =N12*taxa_mensal -> 774.83634 | Q12: =O12*taxa_mensal -> 1394.7054
B13: =C13&"|"&D13 -> Moderado|Papel (CRI) | C13: =$G$8 -> Moderado | D13: =$K$7 -> Papel (CRI) | E13: 0.25 | M13: =M12+1 -> 7 | N13: =FV(taxa_mensal,M13*12,-aporte) -> 119115.14 | O13: =FV(taxa_mensal,M13*12,-sugestao_aporte) -> 214407.25 | P13: =N13*taxa_mensal -> 952.9211 | Q13: =O13*taxa_mensal -> 1715.258
B14: =C14&"|"&D14 -> Moderado|Logística | C14: =$G$8 -> Moderado | D14: =$K$8 -> Logística | E14: 0.2 | M14: =M13+1 -> 8 | N14: =FV(taxa_mensal,M14*12,-aporte) -> 143609.33 | O14: =FV(taxa_mensal,M14*12,-sugestao_aporte) -> 258496.8 | P14: =N14*taxa_mensal -> 1148.8746 | Q14: =O14*taxa_mensal -> 2067.9744
B15: =C15&"|"&D15 -> Moderado|Lajes Corporativas | C15: =$G$8 -> Moderado | D15: =$K$9 -> Lajes Corporativas | E15: 0.15 | M15: =M14+1 -> 9 | N15: =FV(taxa_mensal,M15*12,-aporte) -> 170561.24 | O15: =FV(taxa_mensal,M15*12,-sugestao_aporte) -> 307010.23 | P15: =N15*taxa_mensal -> 1364.4899 | Q15: =O15*taxa_mensal -> 2456.0819
B16: =C16&"|"&D16 -> Moderado|Shoppings | C16: =$G$8 -> Moderado | D16: =$K$10 -> Shoppings | E16: 0.15 | M16: =M15+1 -> 10 | N16: =FV(taxa_mensal,M16*12,-aporte) -> 200217.47 | O16: =FV(taxa_mensal,M16*12,-sugestao_aporte) -> 360391.44 | P16: =N16*taxa_mensal -> 1601.7398 | Q16: =O16*taxa_mensal -> 2883.1316
B17: =C17&"|"&D17 -> Moderado|Fundo de Fundos (FoF) | C17: =$G$8 -> Moderado | D17: =$K$11 -> Fundo de Fundos (FoF) | E17: 0.15 | M17: =M16+1 -> 11 | N17: =FV(taxa_mensal,M17*12,-aporte) -> 232849.37 | O17: =FV(taxa_mensal,M17*12,-sugestao_aporte) -> 419128.86 | P17: =N17*taxa_mensal -> 1862.7949 | Q17: =O17*taxa_mensal -> 3353.0309
B18: =C18&"|"&D18 -> Moderado|Híbridos | C18: =$G$8 -> Moderado | D18: =$K$12 -> Híbridos | E18: 0.1 | M18: =M17+1 -> 12 | N18: =FV(taxa_mensal,M18*12,-aporte) -> 268755.5 | O18: =FV(taxa_mensal,M18*12,-sugestao_aporte) -> 483759.91 | P18: =N18*taxa_mensal -> 2150.044 | Q18: =O18*taxa_mensal -> 3870.0792
B19: =C19&"|"&D19 -> Arrojado|Papel (CRI) | C19: =$G$9 -> Arrojado | D19: =$K$7 -> Papel (CRI) | E19: 0.15 | M19: =M18+1 -> 13 | N19: =FV(taxa_mensal,M19*12,-aporte) -> 308264.42 | O19: =FV(taxa_mensal,M19*12,-sugestao_aporte) -> 554875.95 | P19: =N19*taxa_mensal -> 2466.1153 | Q19: =O19*taxa_mensal -> 4439.0076
B20: =C20&"|"&D20 -> Arrojado|Logística | C20: =$G$9 -> Arrojado | D20: =$K$8 -> Logística | E20: 0.2 | M20: =M19+1 -> 14 | N20: =FV(taxa_mensal,M20*12,-aporte) -> 351737.6 | O20: =FV(taxa_mensal,M20*12,-sugestao_aporte) -> 633127.68 | P20: =N20*taxa_mensal -> 2813.9008 | Q20: =O20*taxa_mensal -> 5065.0215
B21: =C21&"|"&D21 -> Arrojado|Lajes Corporativas | C21: =$G$9 -> Arrojado | D21: =$K$9 -> Lajes Corporativas | E21: 0.2 | M21: =M20+1 -> 15 | N21: =FV(taxa_mensal,M21*12,-aporte) -> 399572.83 | O21: =FV(taxa_mensal,M21*12,-sugestao_aporte) -> 719231.09 | P21: =N21*taxa_mensal -> 3196.5826 | Q21: =O21*taxa_mensal -> 5753.8488
B22: =C22&"|"&D22 -> Arrojado|Shoppings | C22: =$G$9 -> Arrojado | D22: =$K$10 -> Shoppings | E22: 0.2 | M22: =M21+1 -> 16 | N22: =FV(taxa_mensal,M22*12,-aporte) -> 452207.78 | O22: =FV(taxa_mensal,M22*12,-sugestao_aporte) -> 813974.01 | P22: =N22*taxa_mensal -> 3617.6623 | Q22: =O22*taxa_mensal -> 6511.7921
B23: =C23&"|"&D23 -> Arrojado|Fundo de Fundos (FoF) | C23: =$G$9 -> Arrojado | D23: =$K$11 -> Fundo de Fundos (FoF) | E23: 0.05 | M23: =M22+1 -> 17 | N23: =FV(taxa_mensal,M23*12,-aporte) -> 510124.06 | O23: =FV(taxa_mensal,M23*12,-sugestao_aporte) -> 918223.3 | P23: =N23*taxa_mensal -> 4080.9925 | Q23: =O23*taxa_mensal -> 7345.7864
B24: =C24&"|"&D24 -> Arrojado|Híbridos | C24: =$G$9 -> Arrojado | D24: =$K$12 -> Híbridos | E24: 0.2 | M24: =M23+1 -> 18 | N24: =FV(taxa_mensal,M24*12,-aporte) -> 573851.58 | O24: =FV(taxa_mensal,M24*12,-sugestao_aporte) -> 1032932.8 | P24: =N24*taxa_mensal -> 4590.8126 | Q24: =O24*taxa_mensal -> 8263.4627
M25: =M24+1 -> 19 | N25: =FV(taxa_mensal,M25*12,-aporte) -> 643973.43 | O25: =FV(taxa_mensal,M25*12,-sugestao_aporte) -> 1159152.2 | P25: =N25*taxa_mensal -> 5151.7874 | Q25: =O25*taxa_mensal -> 9273.2174
M26: =M25+1 -> 20 | N26: =FV(taxa_mensal,M26*12,-aporte) -> 721131.22 | O26: =FV(taxa_mensal,M26*12,-sugestao_aporte) -> 1298036.2 | P26: =N26*taxa_mensal -> 5769.0498 | Q26: =O26*taxa_mensal -> 10384.29
M27: =M26+1 -> 21 | N27: =FV(taxa_mensal,M27*12,-aporte) -> 806030.92 | O27: =FV(taxa_mensal,M27*12,-sugestao_aporte) -> 1450855.7 | P27: =N27*taxa_mensal -> 6448.2474 | Q27: =O27*taxa_mensal -> 11606.845
M28: =M27+1 -> 22 | N28: =FV(taxa_mensal,M28*12,-aporte) -> 899449.35 | O28: =FV(taxa_mensal,M28*12,-sugestao_aporte) -> 1619008.8 | P28: =N28*taxa_mensal -> 7195.5948 | Q28: =O28*taxa_mensal -> 12952.071
M29: =M28+1 -> 23 | N29: =FV(taxa_mensal,M29*12,-aporte) -> 1002241.3 | O29: =FV(taxa_mensal,M29*12,-sugestao_aporte) -> 1804034.3 | P29: =N29*taxa_mensal -> 8017.93 | Q29: =O29*taxa_mensal -> 14432.274
M30: =M29+1 -> 24 | N30: =FV(taxa_mensal,M30*12,-aporte) -> 1115347.2 | O30: =FV(taxa_mensal,M30*12,-sugestao_aporte) -> 2007624.9 | P30: =N30*taxa_mensal -> 8922.7774 | Q30: =O30*taxa_mensal -> 16060.999
M31: =M30+1 -> 25 | N31: =FV(taxa_mensal,M31*12,-aporte) -> 1239802 | O31: =FV(taxa_mensal,M31*12,-sugestao_aporte) -> 2231643.6 | P31: =N31*taxa_mensal -> 9918.4159 | Q31: =O31*taxa_mensal -> 17853.149
M32: =M31+1 -> 26 | N32: =FV(taxa_mensal,M32*12,-aporte) -> 1376744.4 | O32: =FV(taxa_mensal,M32*12,-sugestao_aporte) -> 2478140 | P32: =N32*taxa_mensal -> 11013.955 | Q32: =O32*taxa_mensal -> 19825.12
M33: =M32+1 -> 27 | N33: =FV(taxa_mensal,M33*12,-aporte) -> 1527427.5 | O33: =FV(taxa_mensal,M33*12,-sugestao_aporte) -> 2749369.5 | P33: =N33*taxa_mensal -> 12219.42 | Q33: =O33*taxa_mensal -> 21994.956
M34: =M33+1 -> 28 | N34: =FV(taxa_mensal,M34*12,-aporte) -> 1693229.9 | O34: =FV(taxa_mensal,M34*12,-sugestao_aporte) -> 3047813.9 | P34: =N34*taxa_mensal -> 13545.839 | Q34: =O34*taxa_mensal -> 24382.511
M35: =M34+1 -> 29 | N35: =FV(taxa_mensal,M35*12,-aporte) -> 1875668.7 | O35: =FV(taxa_mensal,M35*12,-sugestao_aporte) -> 3376203.7 | P35: =N35*taxa_mensal -> 15005.35 | Q35: =O35*taxa_mensal -> 27009.63
M36: =M35+1 -> 30 | N36: =FV(taxa_mensal,M36*12,-aporte) -> 2076413.2 | O36: =FV(taxa_mensal,M36*12,-sugestao_aporte) -> 3737543.8 | P36: =N36*taxa_mensal -> 16611.306 | Q36: =O36*taxa_mensal -> 29900.351
